nvidia_tao_ds/__init__.py
nvidia_tao_ds/annotations/__init__.py
nvidia_tao_ds/annotations/merger.py
nvidia_tao_ds/annotations/slicer.py
nvidia_tao_ds/annotations/conversion/__init__.py
nvidia_tao_ds/annotations/conversion/aicity_to_ovpkl.py
nvidia_tao_ds/annotations/conversion/coco_to_contiguous.py
nvidia_tao_ds/annotations/conversion/coco_to_kitti.py
nvidia_tao_ds/annotations/conversion/coco_to_odvg.py
nvidia_tao_ds/annotations/conversion/kitti_to_coco.py
nvidia_tao_ds/annotations/conversion/mapping.py
nvidia_tao_ds/annotations/conversion/odvg_to_coco.py
nvidia_tao_ds/annotations/entrypoint/__init__.py
nvidia_tao_ds/annotations/entrypoint/annotations.py
nvidia_tao_ds/annotations/scripts/__init__.py
nvidia_tao_ds/annotations/scripts/convert.py
nvidia_tao_ds/annotations/scripts/merge.py
nvidia_tao_ds/annotations/scripts/slice.py
nvidia_tao_ds/api/__init__.py
nvidia_tao_ds/api/app.py
nvidia_tao_ds/augmentation/__init__.py
nvidia_tao_ds/augmentation/dataloader/__init__.py
nvidia_tao_ds/augmentation/dataloader/coco_callable.py
nvidia_tao_ds/augmentation/dataloader/kitti_callable.py
nvidia_tao_ds/augmentation/entrypoint/__init__.py
nvidia_tao_ds/augmentation/entrypoint/augment.py
nvidia_tao_ds/augmentation/pipeline/__init__.py
nvidia_tao_ds/augmentation/pipeline/runner.py
nvidia_tao_ds/augmentation/pipeline/sharded_pipeline.py
nvidia_tao_ds/augmentation/scripts/__init__.py
nvidia_tao_ds/augmentation/scripts/generate.py
nvidia_tao_ds/augmentation/utils/__init__.py
nvidia_tao_ds/augmentation/utils/distributed_utils.py
nvidia_tao_ds/augmentation/utils/file_handlers.py
nvidia_tao_ds/augmentation/utils/helper.py
nvidia_tao_ds/augmentation/utils/kitti.py
nvidia_tao_ds/auto_label/__init__.py
nvidia_tao_ds/auto_label/entrypoint/__init__.py
nvidia_tao_ds/auto_label/entrypoint/auto_label.py
nvidia_tao_ds/auto_label/grounding_dino/__init__.py
nvidia_tao_ds/auto_label/grounding_dino/dataset.py
nvidia_tao_ds/auto_label/grounding_dino/inference.py
nvidia_tao_ds-6.25.11.dist-info/licenses/LICENSE
nvidia_tao_ds-6.25.11.dist-info/METADATA
nvidia_tao_ds-6.25.11.dist-info/WHEEL
nvidia_tao_ds-6.25.11.dist-info/entry_points.txt
nvidia_tao_ds-6.25.11.dist-info/top_level.txt
nvidia_tao_ds-6.25.11.dist-info/RECORD
