Metadata-Version: 2.4
Name: nvidia-tao-ds
Version: 6.25.11
Summary: NVIDIA's package for Data-services for use with TAO Toolkit.
Author: NVIDIA Corporation
License: Apache 2.0
Keywords: nvidia,tao,tf2
Classifier: Environment :: Console
Classifier: License :: Other/Proprietary License
Classifier: Natural Language :: English
Classifier: Operating System :: POSIX :: Linux
Classifier: Programming Language :: Python :: 3.8
Classifier: Topic :: Scientific/Engineering :: Artificial Intelligence
License-File: LICENSE
Dynamic: author
Dynamic: classifier
Dynamic: keywords
Dynamic: license
Dynamic: license-file
Dynamic: summary
